Metadata-Version: 1.1
Name: napalm-brocade
Version: 0.2.2
Summary: Network Automation and Programmability Abstraction Layer with Multivendor support
Home-page: https://github.com/napalm-automation/napalm-brocade
Author: Shiv Haris
Author-email: sharis@brocade.com
License: UNKNOWN
Platform: UNKNOWN
Classifier: Topic :: Utilities
Classifier: Programming Language :: Python
Classifier: Programming Language :: Python :: 2
Classifier: Programming Language :: Python :: 2.7
Classifier: Operating System :: POSIX :: Linux
Classifier: Operating System :: MacOS
